translation_helper/__init__.py
translation_helper/main.py
translation_helper/theme.json
translation_helper/components/CreateKeyWindow.py
translation_helper/components/KeysFrame.py
translation_helper/components/LoadButton.py
translation_helper/components/ModuleSelectionWindow.py
translation_helper/components/ValuesFrame.py
translation_helper/components/__init__.py
translation_helper/data/TranslationManager.py
translation_helper/data/__init__.py
translation_helper-0.2.0.dist-info/METADATA
translation_helper-0.2.0.dist-info/WHEEL
translation_helper-0.2.0.dist-info/entry_points.txt
translation_helper-0.2.0.dist-info/top_level.txt
translation_helper-0.2.0.dist-info/RECORD
